README.md
setup.py
yarp/__init__.py
yarp/file.py
yarp/function_wrappers.py
yarp/general.py
yarp/python_operators.py
yarp/temporal.py
yarp/time_and_date.py
yarp/value.py
yarp/version.py
yarp.egg-info/PKG-INFO
yarp.egg-info/SOURCES.txt
yarp.egg-info/dependency_links.txt
yarp.egg-info/requires.txt
yarp.egg-info/top_level.txt