Metadata-Version: 1.1
Name: yarp
Version: 0.4.0
Summary: Yet Another Reactive(-ish) Programming library.
Home-page: https://github.com/mossblaser/yarp
Author: Jonathan Heathcote
Author-email: UNKNOWN
License: GPLv2
Keywords: asyncio reactive functional
Platform: UNKNOWN
Classifier: Development Status :: 3 - Alpha
Classifier: Intended Audience :: Developers
Classifier: License :: OSI Approved :: GNU General Public License v2 (GPLv2)
Classifier: Operating System :: POSIX :: Linux
Classifier: Operating System :: Microsoft :: Windows
Classifier: Operating System :: MacOS
Classifier: Programming Language :: Python :: 3
Classifier: Programming Language :: Python :: 3.4
Classifier: Programming Language :: Python :: 3.5
